[
  {
    "run_name": "lstm_B32_S100_H128_LR0p0005_L1_D0p2",
    "model_name": "lstm",
    "batch_size": 32,
    "seq_length": 100,
    "hidden_dim": 128,
    "num_layers": 1,
    "dropout": 0.2,
    "learning_rate": 0.0005,
    "val_loss": 4.662640480151392,
    "val_ppl": 105.91538071373752,
    "test_loss": 4.753797220110022,
    "test_ppl": 116.02401785053434,
    "total_time_seconds": 881.0431659221649
  },
  {
    "run_name": "lstm_B32_S100_H128_LR0p0005_L1_D0p3",
    "model_name": "lstm",
    "batch_size": 32,
    "seq_length": 100,
    "hidden_dim": 128,
    "num_layers": 1,
    "dropout": 0.3,
    "learning_rate": 0.0005,
    "val_loss": 4.667884740586362,
    "val_ppl": 106.47228756019025,
    "test_loss": 4.758820865264651,
    "test_ppl": 116.60834785002037,
    "total_time_seconds": 900.2869718074799
  },
  {
    "run_name": "lstm_B32_S100_H128_LR0p0005_L2_D0p2",
    "model_name": "lstm",
    "batch_size": 32,
    "seq_length": 100,
    "hidden_dim": 128,
    "num_layers": 2,
    "dropout": 0.2,
    "learning_rate": 0.0005,
    "val_loss": 4.578909314553597,
    "val_ppl": 97.40809465670159,
    "test_loss": 4.67552394812557,
    "test_ppl": 107.28876611597342,
    "total_time_seconds": 1047.3551807403564
  },
  {
    "run_name": "lstm_B32_S100_H128_LR0p0005_L2_D0p3",
    "model_name": "lstm",
    "batch_size": 32,
    "seq_length": 100,
    "hidden_dim": 128,
    "num_layers": 2,
    "dropout": 0.3,
    "learning_rate": 0.0005,
    "val_loss": 4.634420039738811,
    "val_ppl": 102.9681832205711,
    "test_loss": 4.726315408988077,
    "test_ppl": 112.87888265647439,
    "total_time_seconds": 1058.9152097702026
  },
  {
    "run_name": "lstm_B32_S100_H128_LR0p0005_L3_D0p2",
    "model_name": "lstm",
    "batch_size": 32,
    "seq_length": 100,
    "hidden_dim": 128,
    "num_layers": 3,
    "dropout": 0.2,
    "learning_rate": 0.0005,
    "val_loss": 4.562757403703656,
    "val_ppl": 95.84740577932789,
    "test_loss": 4.655904685039708,
    "test_ppl": 105.20435376432665,
    "total_time_seconds": 1207.898805141449
  },
  {
    "run_name": "lstm_B32_S100_H128_LR0p0005_L3_D0p3",
    "model_name": "lstm",
    "batch_size": 32,
    "seq_length": 100,
    "hidden_dim": 128,
    "num_layers": 3,
    "dropout": 0.3,
    "learning_rate": 0.0005,
    "val_loss": 4.670582480505824,
    "val_ppl": 106.75990989134192,
    "test_loss": 4.76051546878439,
    "test_ppl": 116.80612029232806,
    "total_time_seconds": 1201.8090612888336
  },
  {
    "run_name": "lstm_B32_S100_H128_LR0p001_L1_D0p2",
    "model_name": "lstm",
    "batch_size": 32,
    "seq_length": 100,
    "hidden_dim": 128,
    "num_layers": 1,
    "dropout": 0.2,
    "learning_rate": 0.001,
    "val_loss": 4.656986785466452,
    "val_ppl": 105.31825705671646,
    "test_loss": 4.754229400233381,
    "test_ppl": 116.07417196190595,
    "total_time_seconds": 905.9210155010223
  },
  {
    "run_name": "lstm_B32_S100_H128_LR0p001_L1_D0p3",
    "model_name": "lstm",
    "batch_size": 32,
    "seq_length": 100,
    "hidden_dim": 128,
    "num_layers": 1,
    "dropout": 0.3,
    "learning_rate": 0.001,
    "val_loss": 4.647325033519057,
    "val_ppl": 104.30559808896368,
    "test_loss": 4.743310903277026,
    "test_ppl": 114.81371016476453,
    "total_time_seconds": 905.7377336025238
  },
  {
    "run_name": "lstm_B32_S100_H128_LR0p001_L2_D0p2",
    "model_name": "lstm",
    "batch_size": 32,
    "seq_length": 100,
    "hidden_dim": 128,
    "num_layers": 2,
    "dropout": 0.2,
    "learning_rate": 0.001,
    "val_loss": 4.545903921592001,
    "val_ppl": 94.2455793322967,
    "test_loss": 4.644893087935065,
    "test_ppl": 104.05224075080594,
    "total_time_seconds": 1043.8852190971375
  },
  {
    "run_name": "lstm_B32_S100_H128_LR0p001_L2_D0p3",
    "model_name": "lstm",
    "batch_size": 32,
    "seq_length": 100,
    "hidden_dim": 128,
    "num_layers": 2,
    "dropout": 0.3,
    "learning_rate": 0.001,
    "val_loss": 4.595260017152294,
    "val_ppl": 99.01387750731443,
    "test_loss": 4.689950781307974,
    "test_ppl": 108.84782232812817,
    "total_time_seconds": 1041.8652362823486
  },
  {
    "run_name": "lstm_B32_S100_H128_LR0p001_L3_D0p2",
    "model_name": "lstm",
    "batch_size": 32,
    "seq_length": 100,
    "hidden_dim": 128,
    "num_layers": 3,
    "dropout": 0.2,
    "learning_rate": 0.001,
    "val_loss": 4.524276181273281,
    "val_ppl": 92.22914448085393,
    "test_loss": 4.620255650602635,
    "test_ppl": 101.51998245699049,
    "total_time_seconds": 1206.3170566558838
  },
  {
    "run_name": "lstm_B32_S100_H128_LR0p001_L3_D0p3",
    "model_name": "lstm",
    "batch_size": 32,
    "seq_length": 100,
    "hidden_dim": 128,
    "num_layers": 3,
    "dropout": 0.3,
    "learning_rate": 0.001,
    "val_loss": 4.635239611170201,
    "val_ppl": 103.05260759305709,
    "test_loss": 4.723553443052289,
    "test_ppl": 112.56754517738197,
    "total_time_seconds": 1202.0578846931458
  },
  {
    "run_name": "lstm_B32_S100_H256_LR0p0005_L1_D0p2",
    "model_name": "lstm",
    "batch_size": 32,
    "seq_length": 100,
    "hidden_dim": 256,
    "num_layers": 1,
    "dropout": 0.2,
    "learning_rate": 0.0005,
    "val_loss": 4.658587526198549,
    "val_ppl": 105.48697928486477,
    "test_loss": 4.777887800871149,
    "test_ppl": 118.85304343863541,
    "total_time_seconds": 1522.490929365158
  },
  {
    "run_name": "lstm_B32_S100_H256_LR0p0005_L1_D0p3",
    "model_name": "lstm",
    "batch_size": 32,
    "seq_length": 100,
    "hidden_dim": 256,
    "num_layers": 1,
    "dropout": 0.3,
    "learning_rate": 0.0005,
    "val_loss": 4.590672381649456,
    "val_ppl": 98.560678278874,
    "test_loss": 4.700594371347107,
    "test_ppl": 110.01254132589276,
    "total_time_seconds": 1521.7638187408447
  },
  {
    "run_name": "lstm_B32_S100_H256_LR0p0005_L2_D0p2",
    "model_name": "lstm",
    "batch_size": 32,
    "seq_length": 100,
    "hidden_dim": 256,
    "num_layers": 2,
    "dropout": 0.2,
    "learning_rate": 0.0005,
    "val_loss": 4.423738711131426,
    "val_ppl": 83.40753984814751,
    "test_loss": 4.541715976213239,
    "test_ppl": 93.85170932257674,
    "total_time_seconds": 1963.0549075603485
  },
  {
    "run_name": "lstm_B32_S100_H256_LR0p0005_L2_D0p3",
    "model_name": "lstm",
    "batch_size": 32,
    "seq_length": 100,
    "hidden_dim": 256,
    "num_layers": 2,
    "dropout": 0.3,
    "learning_rate": 0.0005,
    "val_loss": 4.3887341928437085,
    "val_ppl": 80.53840833756678,
    "test_loss": 4.496788040576038,
    "test_ppl": 89.72846376969535,
    "total_time_seconds": 1960.3149881362915
  },
  {
    "run_name": "lstm_B32_S100_H256_LR0p0005_L3_D0p2",
    "model_name": "lstm",
    "batch_size": 32,
    "seq_length": 100,
    "hidden_dim": 256,
    "num_layers": 3,
    "dropout": 0.2,
    "learning_rate": 0.0005,
    "val_loss": 4.33995342898516,
    "val_ppl": 76.70396707352536,
    "test_loss": 4.452727677006506,
    "test_ppl": 85.86082548004664,
    "total_time_seconds": 2541.8761303424835
  },
  {
    "run_name": "lstm_B32_S100_H256_LR0p0005_L3_D0p3",
    "model_name": "lstm",
    "batch_size": 32,
    "seq_length": 100,
    "hidden_dim": 256,
    "num_layers": 3,
    "dropout": 0.3,
    "learning_rate": 0.0005,
    "val_loss": 4.362525227701331,
    "val_ppl": 78.45500123098248,
    "test_loss": 4.465896339738577,
    "test_ppl": 86.99897524034267,
    "total_time_seconds": 2541.9704625606537
  },
  {
    "run_name": "lstm_B32_S100_H256_LR0p001_L1_D0p2",
    "model_name": "lstm",
    "batch_size": 32,
    "seq_length": 100,
    "hidden_dim": 256,
    "num_layers": 1,
    "dropout": 0.2,
    "learning_rate": 0.001,
    "val_loss": 4.709640302281158,
    "val_ppl": 111.01222188034751,
    "test_loss": 4.834903966666031,
    "test_ppl": 125.82649908843399,
    "total_time_seconds": 1562.5861275196075
  },
  {
    "run_name": "lstm_B32_S100_H256_LR0p001_L1_D0p3",
    "model_name": "lstm",
    "batch_size": 32,
    "seq_length": 100,
    "hidden_dim": 256,
    "num_layers": 1,
    "dropout": 0.3,
    "learning_rate": 0.001,
    "val_loss": 4.623013020570168,
    "val_ppl": 101.80029689542425,
    "test_loss": 4.738902158319773,
    "test_ppl": 114.3086399799558,
    "total_time_seconds": 1561.3460552692413
  },
  {
    "run_name": "lstm_B32_S100_H256_LR0p001_L2_D0p2",
    "model_name": "lstm",
    "batch_size": 32,
    "seq_length": 100,
    "hidden_dim": 256,
    "num_layers": 2,
    "dropout": 0.2,
    "learning_rate": 0.001,
    "val_loss": 4.418559932533633,
    "val_ppl": 82.97670722218007,
    "test_loss": 4.536642400677345,
    "test_ppl": 93.3767514722513,
    "total_time_seconds": 1958.2983794212341
  },
  {
    "run_name": "lstm_B32_S100_H256_LR0p001_L2_D0p3",
    "model_name": "lstm",
    "batch_size": 32,
    "seq_length": 100,
    "hidden_dim": 256,
    "num_layers": 2,
    "dropout": 0.3,
    "learning_rate": 0.001,
    "val_loss": 4.370251940705213,
    "val_ppl": 79.06354851670056,
    "test_loss": 4.477358235132757,
    "test_ppl": 88.00188503778979,
    "total_time_seconds": 1960.9281032085419
  },
  {
    "run_name": "lstm_B32_S100_H256_LR0p001_L3_D0p2",
    "model_name": "lstm",
    "batch_size": 32,
    "seq_length": 100,
    "hidden_dim": 256,
    "num_layers": 3,
    "dropout": 0.2,
    "learning_rate": 0.001,
    "val_loss": 4.321966378037849,
    "val_ppl": 75.33662301849553,
    "test_loss": 4.436556789781198,
    "test_ppl": 84.48354568507325,
    "total_time_seconds": 2518.657979249954
  },
  {
    "run_name": "lstm_B32_S100_H256_LR0p001_L3_D0p3",
    "model_name": "lstm",
    "batch_size": 32,
    "seq_length": 100,
    "hidden_dim": 256,
    "num_layers": 3,
    "dropout": 0.3,
    "learning_rate": 0.001,
    "val_loss": 4.335734221581787,
    "val_ppl": 76.3810188995297,
    "test_loss": 4.442405996183656,
    "test_ppl": 84.97915543021116,
    "total_time_seconds": 2522.278461456299
  },
  {
    "run_name": "lstm_B64_S100_H128_LR0p0005_L1_D0p2",
    "model_name": "lstm",
    "batch_size": 64,
    "seq_length": 100,
    "hidden_dim": 128,
    "num_layers": 1,
    "dropout": 0.2,
    "learning_rate": 0.0005,
    "val_loss": 4.682023402022766,
    "val_ppl": 107.9883555168381,
    "test_loss": 4.7772639082510295,
    "test_ppl": 118.77891502844386,
    "total_time_seconds": 826.1096565723419
  },
  {
    "run_name": "lstm_B64_S100_H128_LR0p0005_L1_D0p3",
    "model_name": "lstm",
    "batch_size": 64,
    "seq_length": 100,
    "hidden_dim": 128,
    "num_layers": 1,
    "dropout": 0.3,
    "learning_rate": 0.0005,
    "val_loss": 4.698049397486444,
    "val_ppl": 109.73291825150488,
    "test_loss": 4.785365678259839,
    "test_ppl": 119.74514327425581,
    "total_time_seconds": 823.655844449997
  },
  {
    "run_name": "lstm_B64_S100_H128_LR0p0005_L2_D0p2",
    "model_name": "lstm",
    "batch_size": 64,
    "seq_length": 100,
    "hidden_dim": 128,
    "num_layers": 2,
    "dropout": 0.2,
    "learning_rate": 0.0005,
    "val_loss": 4.608177270617639,
    "val_ppl": 100.30116104438974,
    "test_loss": 4.705844362961915,
    "test_ppl": 110.59162500753591,
    "total_time_seconds": 980.7186269760132
  },
  {
    "run_name": "lstm_B64_S100_H128_LR0p0005_L2_D0p3",
    "model_name": "lstm",
    "batch_size": 64,
    "seq_length": 100,
    "hidden_dim": 128,
    "num_layers": 2,
    "dropout": 0.3,
    "learning_rate": 0.0005,
    "val_loss": 4.67108745935108,
    "val_ppl": 106.81383500173253,
    "test_loss": 4.762209512666808,
    "test_ppl": 117.00416268472836,
    "total_time_seconds": 977.0132625102997
  },
  {
    "run_name": "lstm_B64_S100_H128_LR0p0005_L3_D0p2",
    "model_name": "lstm",
    "batch_size": 64,
    "seq_length": 100,
    "hidden_dim": 128,
    "num_layers": 3,
    "dropout": 0.2,
    "learning_rate": 0.0005,
    "val_loss": 4.593129906430023,
    "val_ppl": 98.80319145715306,
    "test_loss": 4.688478214142987,
    "test_ppl": 108.68765455683086,
    "total_time_seconds": 1082.332041978836
  },
  {
    "run_name": "lstm_B64_S100_H128_LR0p0005_L3_D0p3",
    "model_name": "lstm",
    "batch_size": 64,
    "seq_length": 100,
    "hidden_dim": 128,
    "num_layers": 3,
    "dropout": 0.3,
    "learning_rate": 0.0005,
    "val_loss": 4.704533879250702,
    "val_ppl": 110.44679140613245,
    "test_loss": 4.792394912333167,
    "test_ppl": 120.58982517087506,
    "total_time_seconds": 1078.0326056480408
  }
]